autogit_ui/__init__.py
autogit_ui/core/__init__.py
autogit_ui/core/autogit.py
autogit_ui/ui/__init__.py
autogit_ui/ui/ui.py
autogit_ui-0.1.3.dist-info/METADATA
autogit_ui-0.1.3.dist-info/WHEEL
autogit_ui-0.1.3.dist-info/entry_points.txt
autogit_ui-0.1.3.dist-info/top_level.txt
autogit_ui-0.1.3.dist-info/RECORD
