Metadata-Version: 2.4
Name: autogit-ui
Version: 0.1.3
Summary: 一个功能强大的现代工具
Author-email: optsimauth <optsimauth@gmail.com>
License: MIT
Requires-Python: >=3.13
Requires-Dist: click>=8.3.0
Requires-Dist: pyside6>=6.9.2
Requires-Dist: setuptools>=80.9.0
